setup.py
dm/__init__.py
dm.zopepatches.cookies.egg-info/PKG-INFO
dm.zopepatches.cookies.egg-info/SOURCES.txt
dm.zopepatches.cookies.egg-info/dependency_links.txt
dm.zopepatches.cookies.egg-info/namespace_packages.txt
dm.zopepatches.cookies.egg-info/not-zip-safe
dm.zopepatches.cookies.egg-info/top_level.txt
dm/zopepatches/__init__.py
dm/zopepatches/cookies/README.txt
dm/zopepatches/cookies/VERSION.txt
dm/zopepatches/cookies/__init__.py
dm/zopepatches/cookies/httponly.py
dm/zopepatches/cookies/rfc2965.py
dm/zopepatches/cookies/tests.py