Metadata-Version: 1.0
Name: dm.zopepatches.cookies
Version: 1.0
Summary: Patches for Zope's cookie handling.
Home-page: http://pypi.python.org/pypi/dm.zopepatches.cookies
Author: Dieter Maurer
Author-email: dieter@handshake.de
License: BSD
Keywords: application development menu web cookie
Platform: UNKNOWN
Classifier: Development Status :: 5 - Production/Stable
Classifier: Intended Audience :: Developers
Classifier: License :: OSI Approved :: Zope Public License
Classifier: Framework :: Zope2
Classifier: Operating System :: OS Independent
Classifier: Programming Language :: Python
Classifier: Topic :: Utilities
